README.rst
setup.py
pythonkc_meetups/__init__.py
pythonkc_meetups/client.py
pythonkc_meetups/exceptions.py
pythonkc_meetups/parsers.py
pythonkc_meetups/types.py
pythonkc_meetups.egg-info/PKG-INFO
pythonkc_meetups.egg-info/SOURCES.txt
pythonkc_meetups.egg-info/dependency_links.txt
pythonkc_meetups.egg-info/requires.txt
pythonkc_meetups.egg-info/top_level.txt