Metadata-Version: 1.0
Name: pythonkc-meetups
Version: 0.1.0
Summary: Provides PythonKC Meetup.com events.
Home-page: https://github.com/pythonkc/pythonkc-meetups
Author: Steven Cummings
Author-email: estebistec@gmail.com
License: MIT
Platform: UNKNOWN
Classifier: Development Status :: 4 - Beta
Classifier: License :: OSI Approved :: MIT License
Classifier: Programming Language :: Python
Classifier: Programming Language :: Python :: 2.6
Classifier: Programming Language :: Python :: 2.7
Classifier: Topic :: Internet :: WWW/HTTP :: Dynamic Content
Classifier: Topic :: Software Development :: Libraries
